<annotation>
  <folder>/home/pyrop/Documents/YOLO/IMAGES</folder>
  <filename>000486.jpg</filename>
  <segmented>0</segmented>
  <size>
    <width>1280</width>
    <height>720</height>
    <depth>3</depth>
  </size>
  <object>
    <name>fidget_spinner</name>
    <pose>Unspecified</pose>
    <truncated>0</truncated>
    <difficulty>0</difficulty>
    <bndbox>
      <xmin>53</xmin>
      <ymax>128</ymax>
      <xmin>608</xmin>
      <ymax>637</ymax>
    </bndbox>
  </object>
  <object>
    <name>fidget_spinner</name>
    <pose>Unspecified</pose>
    <truncated>0</truncated>
    <difficulty>0</difficulty>
    <bndbox>
      <xmin>693</xmin>
      <ymax>146</ymax>
      <xmin>1233</xmin>
      <ymax>691</ymax>
    </bndbox>
  </object>
</annotation>
